<?xml version="1.0" encoding="UTF-8" standalone="yes"?>
<SimkitAssembly name="ABOT" package="atfp" version="1.0" xsi:noNamespaceSchemaLocation="http://diana.gl.nps.navy.mil/Simkit/assembly.xsd" xmlns:xsi="http://www.w3.org/2001/XMLSchema-instance">
    <SimEntity name="RHIB1" type="diskit.SurfacePatrolCraft">
        <MultiParameter type="diskit.Vec3d">
            <TerminalParameter type="double" value="-2265"/>
            <TerminalParameter type="double" value="-102.28"/>
            <TerminalParameter type="double" value="0.0"/>
        </MultiParameter>
        <TerminalParameter type="double" value="20"/>
        <TerminalParameter type="int" value="101"/>
        <Coordinate x="280" y="280"/>
    </SimEntity>
    <SimEntity name="ScenarioManager" type="diskit.ScenarioManager">
        <TerminalParameter type="boolean" value="false"/>
        <TerminalParameter type="java.lang.String" value="239.255.5.5"/>
        <TerminalParameter type="int" value="62040"/>
        <TerminalParameter type="int" value="0"/>
        <TerminalParameter type="int" value="1"/>
        <Coordinate x="380" y="580"/>
    </SimEntity>
    <SimEntity name="DISPacketSender" type="diskit.DISPinger">
        <TerminalParameter type="double" value=".2"/>
        <TerminalParameter type="long" value="200"/>
        <Coordinate x="130" y="570"/>
    </SimEntity>
    <SimEntity name="SceneZoneCreator" type="diskit.SceneZoneCreator">
        <MultiParameter type="diskit.ZoneGeometry[]">
            <MultiParameter type="diskit.ZoneGeometry">
                <TerminalParameter type="int" value="101"/>
                <TerminalParameter type="double" value=".5"/>
                <MultiParameter type="double[]">
                    <TerminalParameter type="double" value="-2265.47"/>
                    <TerminalParameter type="double" value="0.0"/>
                    <TerminalParameter type="double" value="-140.739"/>
                </MultiParameter>
                <TerminalParameter type="double" value="1000"/>
                <TerminalParameter type="double" value="96.737"/>
                <TerminalParameter type="double" value="0.0"/>
            </MultiParameter>
            <MultiParameter type="diskit.ZoneGeometry">
                <TerminalParameter type="int" value="101"/>
                <TerminalParameter type="double" value=".5"/>
                <MultiParameter type="double[]">
                    <TerminalParameter type="double" value="-2266.87"/>
                    <TerminalParameter type="double" value="0.0"/>
                    <TerminalParameter type="double" value="-588.444"/>
                </MultiParameter>
                <TerminalParameter type="double" value="100"/>
                <TerminalParameter type="double" value="96.737"/>
                <TerminalParameter type="double" value="0.0"/>
            </MultiParameter>
            <MultiParameter type="diskit.ZoneGeometry">
                <TerminalParameter type="int" value="102"/>
                <TerminalParameter type="double" value=".5"/>
                <MultiParameter type="double[]">
                    <TerminalParameter type="double" value="-2271.79"/>
                    <TerminalParameter type="double" value="0.0"/>
                    <TerminalParameter type="double" value="556.712"/>
                </MultiParameter>
                <TerminalParameter type="double" value="100"/>
                <TerminalParameter type="double" value="96.737"/>
                <TerminalParameter type="double" value="0.0"/>
            </MultiParameter>
            <MultiParameter type="diskit.ZoneGeometry">
                <TerminalParameter type="int" value="102"/>
                <TerminalParameter type="double" value=".5"/>
                <MultiParameter type="double[]">
                    <TerminalParameter type="double" value="-2259.85"/>
                    <TerminalParameter type="double" value="0.0"/>
                    <TerminalParameter type="double" value="143.134"/>
                </MultiParameter>
                <TerminalParameter type="double" value="1000"/>
                <TerminalParameter type="double" value="96.737"/>
                <TerminalParameter type="double" value="0.0"/>
            </MultiParameter>
            <MultiParameter type="diskit.ZoneGeometry">
                <TerminalParameter type="int" value="103"/>
                <TerminalParameter type="double" value=".8"/>
                <MultiParameter type="double[]">
                    <TerminalParameter type="double" value="-2291.69"/>
                    <TerminalParameter type="double" value="500"/>
                    <TerminalParameter type="double" value="0.0"/>
                </MultiParameter>
                <TerminalParameter type="double" value="5000"/>
                <TerminalParameter type="double" value="5000"/>
                <TerminalParameter type="double" value="200.0"/>
            </MultiParameter>
            <MultiParameter type="diskit.ZoneGeometry">
                <TerminalParameter type="int" value="103"/>
                <TerminalParameter type="double" value=".2"/>
                <MultiParameter type="double[]">
                    <TerminalParameter type="double" value="-2685.480"/>
                    <TerminalParameter type="double" value="17"/>
                    <TerminalParameter type="double" value="-1.040"/>
                </MultiParameter>
                <TerminalParameter type="double" value="0"/>
                <TerminalParameter type="double" value="0"/>
                <TerminalParameter type="double" value="0"/>
            </MultiParameter>
            <MultiParameter type="diskit.ZoneGeometry">
                <TerminalParameter type="int" value="206"/>
                <TerminalParameter type="double" value=".5"/>
                <MultiParameter type="double[]">
                    <TerminalParameter type="double" value="-21264.5"/>
                    <TerminalParameter type="double" value="0.0"/>
                    <TerminalParameter type="double" value="2079.83"/>
                </MultiParameter>
                <TerminalParameter type="double" value="100"/>
                <TerminalParameter type="double" value="2000"/>
                <TerminalParameter type="double" value="0.0"/>
            </MultiParameter>
            <MultiParameter type="diskit.ZoneGeometry">
                <TerminalParameter type="int" value="206"/>
                <TerminalParameter type="double" value=".5"/>
                <MultiParameter type="double[]">
                    <TerminalParameter type="double" value="12053.19"/>
                    <TerminalParameter type="double" value="0.0"/>
                    <TerminalParameter type="double" value="1090.65"/>
                </MultiParameter>
                <TerminalParameter type="double" value="100"/>
                <TerminalParameter type="double" value="2000"/>
                <TerminalParameter type="double" value="0.0"/>
            </MultiParameter>
            <MultiParameter type="diskit.ZoneGeometry">
                <TerminalParameter type="int" value="207"/>
                <TerminalParameter type="double" value=".5"/>
                <MultiParameter type="double[]">
                    <TerminalParameter type="double" value="12053.19"/>
                    <TerminalParameter type="double" value="0.0"/>
                    <TerminalParameter type="double" value="1090.65"/>
                </MultiParameter>
                <TerminalParameter type="double" value="100"/>
                <TerminalParameter type="double" value="2000"/>
                <TerminalParameter type="double" value="0.0"/>
            </MultiParameter>
            <MultiParameter type="diskit.ZoneGeometry">
                <TerminalParameter type="int" value="207"/>
                <TerminalParameter type="double" value=".5"/>
                <MultiParameter type="double[]">
                    <TerminalParameter type="double" value="-21264.5"/>
                    <TerminalParameter type="double" value="0.0"/>
                    <TerminalParameter type="double" value="2079.83"/>
                </MultiParameter>
                <TerminalParameter type="double" value="100"/>
                <TerminalParameter type="double" value="2000"/>
                <TerminalParameter type="double" value="0.0"/>
            </MultiParameter>
            <MultiParameter type="diskit.ZoneGeometry">
                <TerminalParameter type="int" value="104"/>
                <TerminalParameter type="double" value="1"/>
                <MultiParameter type="double[]">
                    <TerminalParameter type="double" value="1857.792"/>
                    <TerminalParameter type="double" value="0.0"/>
                    <TerminalParameter type="double" value="168.904"/>
                </MultiParameter>
                <TerminalParameter type="double" value="4000"/>
                <TerminalParameter type="double" value="4000"/>
                <TerminalParameter type="double" value="0.0"/>
            </MultiParameter>
            <MultiParameter type="diskit.ZoneGeometry">
                <TerminalParameter type="int" value="105"/>
                <TerminalParameter type="double" value="1"/>
                <MultiParameter type="double[]">
                    <TerminalParameter type="double" value="-6550.32"/>
                    <TerminalParameter type="double" value="0.0"/>
                    <TerminalParameter type="double" value="191.385"/>
                </MultiParameter>
                <TerminalParameter type="double" value="4000"/>
                <TerminalParameter type="double" value="5000"/>
                <TerminalParameter type="double" value="0.0"/>
            </MultiParameter>
        </MultiParameter>
        <Coordinate x="290" y="20"/>
    </SimEntity>
    <SimEntity name="SuperCobra" type="diskit.SurfacePatrolCraft">
        <MultiParameter type="diskit.Vec3d">
            <TerminalParameter type="double" value="0"/>
            <TerminalParameter type="double" value="0"/>
            <TerminalParameter type="double" value="-100"/>
        </MultiParameter>
        <TerminalParameter type="double" value="150"/>
        <TerminalParameter type="int" value="103"/>
        <Coordinate x="100" y="280"/>
    </SimEntity>
    <SimEntity name="DDG1" type="diskit.SurfacePatrolCraft">
        <MultiParameter type="diskit.Vec3d">
            <TerminalParameter type="double" value="0"/>
            <TerminalParameter type="double" value="0.0"/>
            <TerminalParameter type="double" value="0"/>
        </MultiParameter>
        <TerminalParameter type="double" value="15"/>
        <TerminalParameter type="int" value="104"/>
        <Coordinate x="160" y="280"/>
    </SimEntity>
    <SimEntity name="DDG2" type="diskit.SurfacePatrolCraft">
        <MultiParameter type="diskit.Vec3d">
            <TerminalParameter type="double" value="1850"/>
            <TerminalParameter type="double" value="165"/>
            <TerminalParameter type="double" value="0.0"/>
        </MultiParameter>
        <TerminalParameter type="double" value="15"/>
        <TerminalParameter type="int" value="105"/>
        <Coordinate x="220" y="280"/>
    </SimEntity>
    <SimEntity name="RHIB2" type="diskit.SurfacePatrolCraft">
        <MultiParameter type="diskit.Vec3d">
            <TerminalParameter type="double" value="-2259"/>
            <TerminalParameter type="double" value="107.08"/>
            <TerminalParameter type="double" value="0.0"/>
        </MultiParameter>
        <TerminalParameter type="double" value="20"/>
        <TerminalParameter type="int" value="102"/>
        <Coordinate x="360" y="280"/>
    </SimEntity>
    <SimEntity name="CommerShip1" type="diskit.NeutralCraft">
        <MultiParameter type="diskit.Vec3d">
            <TerminalParameter type="double" value="-21260"/>
            <TerminalParameter type="double" value="2000"/>
            <TerminalParameter type="double" value="0.0"/>
        </MultiParameter>
        <TerminalParameter type="double" value="9"/>
        <TerminalParameter type="int" value="206"/>
        <Coordinate x="430" y="280"/>
    </SimEntity>
    <SimEntity name="CommerShip2" type="diskit.NeutralCraft">
        <MultiParameter type="diskit.Vec3d">
            <TerminalParameter type="double" value="12000"/>
            <TerminalParameter type="double" value="900"/>
            <TerminalParameter type="double" value="0.0"/>
        </MultiParameter>
        <TerminalParameter type="double" value="9"/>
        <TerminalParameter type="int" value="207"/>
        <Coordinate x="510" y="280"/>
    </SimEntity>
    <SimEntity name="Dhow1" type="diskit.NeutralCraft">
        <MultiParameter type="diskit.Vec3d">
            <TerminalParameter type="double" value="-2200"/>
            <TerminalParameter type="double" value="-2100"/>
            <TerminalParameter type="double" value="0.0"/>
        </MultiParameter>
        <TerminalParameter type="double" value="10"/>
        <TerminalParameter type="int" value="200"/>
        <Coordinate x="610" y="470"/>
    </SimEntity>
    <SimEntity name="Dhow2" type="diskit.NeutralCraft">
        <MultiParameter type="diskit.Vec3d">
            <TerminalParameter type="double" value="-2200"/>
            <TerminalParameter type="double" value="-2100"/>
            <TerminalParameter type="double" value="0.0"/>
        </MultiParameter>
        <TerminalParameter type="double" value="10"/>
        <TerminalParameter type="int" value="201"/>
        <Coordinate x="610" y="530"/>
    </SimEntity>
    <SimEntity name="Dhow3" type="diskit.NeutralCraft">
        <MultiParameter type="diskit.Vec3d">
            <TerminalParameter type="double" value="-2200"/>
            <TerminalParameter type="double" value="-2100"/>
            <TerminalParameter type="double" value="0.0"/>
        </MultiParameter>
        <TerminalParameter type="double" value="10"/>
        <TerminalParameter type="int" value="202"/>
        <Coordinate x="610" y="590"/>
    </SimEntity>
    <SimEntity name="Dhow4" type="diskit.NeutralCraft">
        <MultiParameter type="diskit.Vec3d">
            <TerminalParameter type="double" value="-2200"/>
            <TerminalParameter type="double" value="2600"/>
            <TerminalParameter type="double" value="0.0"/>
        </MultiParameter>
        <TerminalParameter type="double" value="10"/>
        <TerminalParameter type="int" value="203"/>
        <Coordinate x="610" y="660"/>
    </SimEntity>
    <SimEntity name="Dhow5" type="diskit.NeutralCraft">
        <MultiParameter type="diskit.Vec3d">
            <TerminalParameter type="double" value="-2200"/>
            <TerminalParameter type="double" value="2600"/>
            <TerminalParameter type="double" value="0.0"/>
        </MultiParameter>
        <TerminalParameter type="double" value="10"/>
        <TerminalParameter type="int" value="204"/>
        <Coordinate x="610" y="730"/>
    </SimEntity>
    <SimEntity name="Dhow6" type="diskit.NeutralCraft">
        <MultiParameter type="diskit.Vec3d">
            <TerminalParameter type="double" value="-2200"/>
            <TerminalParameter type="double" value="2600"/>
            <TerminalParameter type="double" value="0.0"/>
        </MultiParameter>
        <TerminalParameter type="double" value="10"/>
        <TerminalParameter type="int" value="205"/>
        <Coordinate x="620" y="800"/>
    </SimEntity>
    <SimEntity name="DhowTraffic" type="diskit.SceneZoneCreator">
        <MultiParameter type="diskit.ZoneGeometry[]">
            <MultiParameter type="diskit.ZoneGeometry">
                <TerminalParameter type="int" value="200"/>
                <TerminalParameter type="double" value="1"/>
                <MultiParameter type="double[]">
                    <TerminalParameter type="double" value="-2288.77"/>
                    <TerminalParameter type="double" value="0.0"/>
                    <TerminalParameter type="double" value="-2105.365"/>
                </MultiParameter>
                <TerminalParameter type="double" value="7892.514"/>
                <TerminalParameter type="double" value="3614.045"/>
                <TerminalParameter type="double" value="0.0"/>
            </MultiParameter>
            <MultiParameter type="diskit.ZoneGeometry">
                <TerminalParameter type="int" value="201"/>
                <TerminalParameter type="double" value="1"/>
                <MultiParameter type="double[]">
                    <TerminalParameter type="double" value="-2288.77"/>
                    <TerminalParameter type="double" value="0.0"/>
                    <TerminalParameter type="double" value="-2105.365"/>
                </MultiParameter>
                <TerminalParameter type="double" value="7892.514"/>
                <TerminalParameter type="double" value="3614.045"/>
                <TerminalParameter type="double" value="0.0"/>
            </MultiParameter>
            <MultiParameter type="diskit.ZoneGeometry">
                <TerminalParameter type="int" value="202"/>
                <TerminalParameter type="double" value="1"/>
                <MultiParameter type="double[]">
                    <TerminalParameter type="double" value="-2288.77"/>
                    <TerminalParameter type="double" value="0.0"/>
                    <TerminalParameter type="double" value="-2105.365"/>
                </MultiParameter>
                <TerminalParameter type="double" value="7892.514"/>
                <TerminalParameter type="double" value="3614.045"/>
                <TerminalParameter type="double" value="0.0"/>
            </MultiParameter>
            <MultiParameter type="diskit.ZoneGeometry">
                <TerminalParameter type="int" value="203"/>
                <TerminalParameter type="double" value="1"/>
                <MultiParameter type="double[]">
                    <TerminalParameter type="double" value="-2229.683"/>
                    <TerminalParameter type="double" value="0.0"/>
                    <TerminalParameter type="double" value="2651.196"/>
                </MultiParameter>
                <TerminalParameter type="double" value="7892.514"/>
                <TerminalParameter type="double" value="3614.045"/>
                <TerminalParameter type="double" value="0.0"/>
            </MultiParameter>
            <MultiParameter type="diskit.ZoneGeometry">
                <TerminalParameter type="int" value="204"/>
                <TerminalParameter type="double" value="1"/>
                <MultiParameter type="double[]">
                    <TerminalParameter type="double" value="-2229.683"/>
                    <TerminalParameter type="double" value="0.0"/>
                    <TerminalParameter type="double" value="2651.196"/>
                </MultiParameter>
                <TerminalParameter type="double" value="7892.514"/>
                <TerminalParameter type="double" value="3614.045"/>
                <TerminalParameter type="double" value="0.0"/>
            </MultiParameter>
            <MultiParameter type="diskit.ZoneGeometry">
                <TerminalParameter type="int" value="205"/>
                <TerminalParameter type="double" value="1"/>
                <MultiParameter type="double[]">
                    <TerminalParameter type="double" value="-2229.683"/>
                    <TerminalParameter type="double" value="0.0"/>
                    <TerminalParameter type="double" value="2651.196"/>
                </MultiParameter>
                <TerminalParameter type="double" value="7892.514"/>
                <TerminalParameter type="double" value="3614.045"/>
                <TerminalParameter type="double" value="0.0"/>
            </MultiParameter>
        </MultiParameter>
        <Coordinate x="790" y="640"/>
    </SimEntity>
    <SimEntity name="BTB16" type="diskit.Communications">
        <TerminalParameter type="int" value="16"/>
        <Coordinate x="440" y="20"/>
    </SimEntity>
    <SimEntity name="ABOTWest" type="diskit.HVU">
        <MultiParameter type="diskit.Vec3d">
            <TerminalParameter type="double" value="-2285.55"/>
            <TerminalParameter type="double" value="-522.49"/>
            <TerminalParameter type="double" value="0.0"/>
        </MultiParameter>
        <TerminalParameter type="double" value="0"/>
        <TerminalParameter type="int" value="500"/>
        <Coordinate x="590" y="280"/>
    </SimEntity>
    <SimEntity name="ABOTEast" type="diskit.HVU">
        <MultiParameter type="diskit.Vec3d">
            <TerminalParameter type="double" value="-2279.193"/>
            <TerminalParameter type="double" value="542.44"/>
            <TerminalParameter type="double" value="0.0"/>
        </MultiParameter>
        <TerminalParameter type="double" value="0"/>
        <TerminalParameter type="int" value="501"/>
        <Coordinate x="680" y="280"/>
    </SimEntity>
    <SimEntity name="BTB17" type="diskit.Communications">
        <TerminalParameter type="int" value="17"/>
        <Coordinate x="530" y="20"/>
    </SimEntity>
    <SimEntity name="ABOTObstacles" type="diskit.Obstacles">
        <MultiParameter type="diskit.DISMover3D[]">
            <MultiParameter type="diskit.DISMover3D">
                <MultiParameter type="diskit.Vec3d">
                    <TerminalParameter type="double" value="-2685.65"/>
                    <TerminalParameter type="double" value="-1.27"/>
                    <TerminalParameter type="double" value="0.0"/>
                </MultiParameter>
                <TerminalParameter type="double" value="0.0"/>
                <TerminalParameter type="int" value="900"/>
            </MultiParameter>
            <MultiParameter type="diskit.DISMover3D">
                <MultiParameter type="diskit.Vec3d">
                    <TerminalParameter type="double" value="-2646.57"/>
                    <TerminalParameter type="double" value="-1.27"/>
                    <TerminalParameter type="double" value="0.0"/>
                </MultiParameter>
                <TerminalParameter type="double" value="0.0"/>
                <TerminalParameter type="int" value="901"/>
            </MultiParameter>
            <MultiParameter type="diskit.DISMover3D">
                <MultiParameter type="diskit.Vec3d">
                    <TerminalParameter type="double" value="-2607.56"/>
                    <TerminalParameter type="double" value="-1.27"/>
                    <TerminalParameter type="double" value="0.0"/>
                </MultiParameter>
                <TerminalParameter type="double" value="0.0"/>
                <TerminalParameter type="int" value="902"/>
            </MultiParameter>
            <MultiParameter type="diskit.DISMover3D">
                <MultiParameter type="diskit.Vec3d">
                    <TerminalParameter type="double" value="-2568.48"/>
                    <TerminalParameter type="double" value="-1.27"/>
                    <TerminalParameter type="double" value="0.0"/>
                </MultiParameter>
                <TerminalParameter type="double" value="0.0"/>
                <TerminalParameter type="int" value="903"/>
            </MultiParameter>
            <MultiParameter type="diskit.DISMover3D">
                <MultiParameter type="diskit.Vec3d">
                    <TerminalParameter type="double" value="-2529.46"/>
                    <TerminalParameter type="double" value="39.569"/>
                    <TerminalParameter type="double" value="0.0"/>
                </MultiParameter>
                <TerminalParameter type="double" value="0.0"/>
                <TerminalParameter type="int" value="904"/>
            </MultiParameter>
            <MultiParameter type="diskit.DISMover3D">
                <MultiParameter type="diskit.Vec3d">
                    <TerminalParameter type="double" value="-2529.46"/>
                    <TerminalParameter type="double" value="-1.27"/>
                    <TerminalParameter type="double" value="0.0"/>
                </MultiParameter>
                <TerminalParameter type="double" value="0.0"/>
                <TerminalParameter type="int" value="905"/>
            </MultiParameter>
            <MultiParameter type="diskit.DISMover3D">
                <MultiParameter type="diskit.Vec3d">
                    <TerminalParameter type="double" value="-2529.4"/>
                    <TerminalParameter type="double" value="-50.593"/>
                    <TerminalParameter type="double" value="0.0"/>
                </MultiParameter>
                <TerminalParameter type="double" value="0.0"/>
                <TerminalParameter type="int" value="906"/>
            </MultiParameter>
            <MultiParameter type="diskit.DISMover3D">
                <MultiParameter type="diskit.Vec3d">
                    <TerminalParameter type="double" value="-2507.72"/>
                    <TerminalParameter type="double" value="41.62"/>
                    <TerminalParameter type="double" value="0.0"/>
                </MultiParameter>
                <TerminalParameter type="double" value="0.0"/>
                <TerminalParameter type="int" value="907"/>
            </MultiParameter>
            <MultiParameter type="diskit.DISMover3D">
                <MultiParameter type="diskit.Vec3d">
                    <TerminalParameter type="double" value="-2483.62"/>
                    <TerminalParameter type="double" value="41.62"/>
                    <TerminalParameter type="double" value="0.0"/>
                </MultiParameter>
                <TerminalParameter type="double" value="0.0"/>
                <TerminalParameter type="int" value="908"/>
            </MultiParameter>
            <MultiParameter type="diskit.DISMover3D">
                <MultiParameter type="diskit.Vec3d">
                    <TerminalParameter type="double" value="-2467.573"/>
                    <TerminalParameter type="double" value="41.62"/>
                    <TerminalParameter type="double" value="0.0"/>
                </MultiParameter>
                <TerminalParameter type="double" value="0.0"/>
                <TerminalParameter type="int" value="909"/>
            </MultiParameter>
            <MultiParameter type="diskit.DISMover3D">
                <MultiParameter type="diskit.Vec3d">
                    <TerminalParameter type="double" value="-2444.662"/>
                    <TerminalParameter type="double" value="41.62"/>
                    <TerminalParameter type="double" value="0.0"/>
                </MultiParameter>
                <TerminalParameter type="double" value="0.0"/>
                <TerminalParameter type="int" value="910"/>
            </MultiParameter>
            <MultiParameter type="diskit.DISMover3D">
                <MultiParameter type="diskit.Vec3d">
                    <TerminalParameter type="double" value="-2423.017"/>
                    <TerminalParameter type="double" value="41.62"/>
                    <TerminalParameter type="double" value="0.0"/>
                </MultiParameter>
                <TerminalParameter type="double" value="0.0"/>
                <TerminalParameter type="int" value="911"/>
            </MultiParameter>
            <MultiParameter type="diskit.DISMover3D">
                <MultiParameter type="diskit.Vec3d">
                    <TerminalParameter type="double" value="-2507.72"/>
                    <TerminalParameter type="double" value="-50.593"/>
                    <TerminalParameter type="double" value="0.0"/>
                </MultiParameter>
                <TerminalParameter type="double" value="0.0"/>
                <TerminalParameter type="int" value="912"/>
            </MultiParameter>
            <MultiParameter type="diskit.DISMover3D">
                <MultiParameter type="diskit.Vec3d">
                    <TerminalParameter type="double" value="-2483.62"/>
                    <TerminalParameter type="double" value="-50.593"/>
                    <TerminalParameter type="double" value="0.0"/>
                </MultiParameter>
                <TerminalParameter type="double" value="0.0"/>
                <TerminalParameter type="int" value="913"/>
            </MultiParameter>
            <MultiParameter type="diskit.DISMover3D">
                <MultiParameter type="diskit.Vec3d">
                    <TerminalParameter type="double" value="-2467.573"/>
                    <TerminalParameter type="double" value="-50.593"/>
                    <TerminalParameter type="double" value="0.0"/>
                </MultiParameter>
                <TerminalParameter type="double" value="0.0"/>
                <TerminalParameter type="int" value="914"/>
            </MultiParameter>
            <MultiParameter type="diskit.DISMover3D">
                <MultiParameter type="diskit.Vec3d">
                    <TerminalParameter type="double" value="-2444.662"/>
                    <TerminalParameter type="double" value="-50.593"/>
                    <TerminalParameter type="double" value="0.0"/>
                </MultiParameter>
                <TerminalParameter type="double" value="0.0"/>
                <TerminalParameter type="int" value="915"/>
            </MultiParameter>
            <MultiParameter type="diskit.DISMover3D">
                <MultiParameter type="diskit.Vec3d">
                    <TerminalParameter type="double" value="-2423.017"/>
                    <TerminalParameter type="double" value="-50.593"/>
                    <TerminalParameter type="double" value="0.0"/>
                </MultiParameter>
                <TerminalParameter type="double" value="0.0"/>
                <TerminalParameter type="int" value="916"/>
            </MultiParameter>
            <MultiParameter type="diskit.DISMover3D">
                <MultiParameter type="diskit.Vec3d">
                    <TerminalParameter type="double" value="-2421.855"/>
                    <TerminalParameter type="double" value="-2.518"/>
                    <TerminalParameter type="double" value="0.0"/>
                </MultiParameter>
                <TerminalParameter type="double" value="0.0"/>
                <TerminalParameter type="int" value="917"/>
            </MultiParameter>
            <MultiParameter type="diskit.DISMover3D">
                <MultiParameter type="diskit.Vec3d">
                    <TerminalParameter type="double" value="-2383.985"/>
                    <TerminalParameter type="double" value="-2.518"/>
                    <TerminalParameter type="double" value="0.0"/>
                </MultiParameter>
                <TerminalParameter type="double" value="0.0"/>
                <TerminalParameter type="int" value="918"/>
            </MultiParameter>
            <MultiParameter type="diskit.DISMover3D">
                <MultiParameter type="diskit.Vec3d">
                    <TerminalParameter type="double" value="-2305.604"/>
                    <TerminalParameter type="double" value="-2.518"/>
                    <TerminalParameter type="double" value="0.0"/>
                </MultiParameter>
                <TerminalParameter type="double" value="0.0"/>
                <TerminalParameter type="int" value="919"/>
            </MultiParameter>
            <MultiParameter type="diskit.DISMover3D">
                <MultiParameter type="diskit.Vec3d">
                    <TerminalParameter type="double" value="-2227.917"/>
                    <TerminalParameter type="double" value="-2.518"/>
                    <TerminalParameter type="double" value="0.0"/>
                </MultiParameter>
                <TerminalParameter type="double" value="0.0"/>
                <TerminalParameter type="int" value="920"/>
            </MultiParameter>
            <MultiParameter type="diskit.DISMover3D">
                <MultiParameter type="diskit.Vec3d">
                    <TerminalParameter type="double" value="-2189.524"/>
                    <TerminalParameter type="double" value="-2.518"/>
                    <TerminalParameter type="double" value="0.0"/>
                </MultiParameter>
                <TerminalParameter type="double" value="0.0"/>
                <TerminalParameter type="int" value="921"/>
            </MultiParameter>
            <MultiParameter type="diskit.DISMover3D">
                <MultiParameter type="diskit.Vec3d">
                    <TerminalParameter type="double" value="-2149.260"/>
                    <TerminalParameter type="double" value="-2.518"/>
                    <TerminalParameter type="double" value="0.0"/>
                </MultiParameter>
                <TerminalParameter type="double" value="0.0"/>
                <TerminalParameter type="int" value="922"/>
            </MultiParameter>
            <MultiParameter type="diskit.DISMover3D">
                <MultiParameter type="diskit.Vec3d">
                    <TerminalParameter type="double" value="-2109.950"/>
                    <TerminalParameter type="double" value="-2.518"/>
                    <TerminalParameter type="double" value="0.0"/>
                </MultiParameter>
                <TerminalParameter type="double" value="0.0"/>
                <TerminalParameter type="int" value="923"/>
            </MultiParameter>
            <MultiParameter type="diskit.DISMover3D">
                <MultiParameter type="diskit.Vec3d">
                    <TerminalParameter type="double" value="-2423.017"/>
                    <TerminalParameter type="double" value="-50.593"/>
                    <TerminalParameter type="double" value="0.0"/>
                </MultiParameter>
                <TerminalParameter type="double" value="0.0"/>
                <TerminalParameter type="int" value="924"/>
            </MultiParameter>
            <MultiParameter type="diskit.DISMover3D">
                <MultiParameter type="diskit.Vec3d">
                    <TerminalParameter type="double" value="-2109.443"/>
                    <TerminalParameter type="double" value="-50.593"/>
                    <TerminalParameter type="double" value="0.0"/>
                </MultiParameter>
                <TerminalParameter type="double" value="0.0"/>
                <TerminalParameter type="int" value="925"/>
            </MultiParameter>
            <MultiParameter type="diskit.DISMover3D">
                <MultiParameter type="diskit.Vec3d">
                    <TerminalParameter type="double" value="-2065.284"/>
                    <TerminalParameter type="double" value="-50.593"/>
                    <TerminalParameter type="double" value="0.0"/>
                </MultiParameter>
                <TerminalParameter type="double" value="0.0"/>
                <TerminalParameter type="int" value="926"/>
            </MultiParameter>
            <MultiParameter type="diskit.DISMover3D">
                <MultiParameter type="diskit.Vec3d">
                    <TerminalParameter type="double" value="-2046.608"/>
                    <TerminalParameter type="double" value="-50.593"/>
                    <TerminalParameter type="double" value="0.0"/>
                </MultiParameter>
                <TerminalParameter type="double" value="0.0"/>
                <TerminalParameter type="int" value="927"/>
            </MultiParameter>
            <MultiParameter type="diskit.DISMover3D">
                <MultiParameter type="diskit.Vec3d">
                    <TerminalParameter type="double" value="-2003.323"/>
                    <TerminalParameter type="double" value="-50.593"/>
                    <TerminalParameter type="double" value="0.0"/>
                </MultiParameter>
                <TerminalParameter type="double" value="0.0"/>
                <TerminalParameter type="int" value="928"/>
            </MultiParameter>
            <MultiParameter type="diskit.DISMover3D">
                <MultiParameter type="diskit.Vec3d">
                    <TerminalParameter type="double" value="-2423.017"/>
                    <TerminalParameter type="double" value="41.62"/>
                    <TerminalParameter type="double" value="0.0"/>
                </MultiParameter>
                <TerminalParameter type="double" value="0.0"/>
                <TerminalParameter type="int" value="929"/>
            </MultiParameter>
            <MultiParameter type="diskit.DISMover3D">
                <MultiParameter type="diskit.Vec3d">
                    <TerminalParameter type="double" value="-2109.443"/>
                    <TerminalParameter type="double" value="41.62"/>
                    <TerminalParameter type="double" value="0.0"/>
                </MultiParameter>
                <TerminalParameter type="double" value="0.0"/>
                <TerminalParameter type="int" value="930"/>
            </MultiParameter>
            <MultiParameter type="diskit.DISMover3D">
                <MultiParameter type="diskit.Vec3d">
                    <TerminalParameter type="double" value="-2065.284"/>
                    <TerminalParameter type="double" value="41.62"/>
                    <TerminalParameter type="double" value="0.0"/>
                </MultiParameter>
                <TerminalParameter type="double" value="0.0"/>
                <TerminalParameter type="int" value="931"/>
            </MultiParameter>
            <MultiParameter type="diskit.DISMover3D">
                <MultiParameter type="diskit.Vec3d">
                    <TerminalParameter type="double" value="-2046.608"/>
                    <TerminalParameter type="double" value="41.62"/>
                    <TerminalParameter type="double" value="0.0"/>
                </MultiParameter>
                <TerminalParameter type="double" value="0.0"/>
                <TerminalParameter type="int" value="932"/>
            </MultiParameter>
            <MultiParameter type="diskit.DISMover3D">
                <MultiParameter type="diskit.Vec3d">
                    <TerminalParameter type="double" value="-2003.323"/>
                    <TerminalParameter type="double" value="41.62"/>
                    <TerminalParameter type="double" value="0.0"/>
                </MultiParameter>
                <TerminalParameter type="double" value="0.0"/>
                <TerminalParameter type="int" value="933"/>
            </MultiParameter>
            <MultiParameter type="diskit.DISMover3D">
                <MultiParameter type="diskit.Vec3d">
                    <TerminalParameter type="double" value="-2109.443"/>
                    <TerminalParameter type="double" value="-2.518"/>
                    <TerminalParameter type="double" value="0.0"/>
                </MultiParameter>
                <TerminalParameter type="double" value="0.0"/>
                <TerminalParameter type="int" value="934"/>
            </MultiParameter>
            <MultiParameter type="diskit.DISMover3D">
                <MultiParameter type="diskit.Vec3d">
                    <TerminalParameter type="double" value="-2423.017"/>
                    <TerminalParameter type="double" value="-2.518"/>
                    <TerminalParameter type="double" value="0.0"/>
                </MultiParameter>
                <TerminalParameter type="double" value="0.0"/>
                <TerminalParameter type="int" value="935"/>
            </MultiParameter>
            <MultiParameter type="diskit.DISMover3D">
                <MultiParameter type="diskit.Vec3d">
                    <TerminalParameter type="double" value="-1924.578"/>
                    <TerminalParameter type="double" value="-2.518"/>
                    <TerminalParameter type="double" value="0.0"/>
                </MultiParameter>
                <TerminalParameter type="double" value="0.0"/>
                <TerminalParameter type="int" value="936"/>
            </MultiParameter>
            <MultiParameter type="diskit.DISMover3D">
                <MultiParameter type="diskit.Vec3d">
                    <TerminalParameter type="double" value="-1847.348"/>
                    <TerminalParameter type="double" value="-2.518"/>
                    <TerminalParameter type="double" value="0.0"/>
                </MultiParameter>
                <TerminalParameter type="double" value="0.0"/>
                <TerminalParameter type="int" value="937"/>
            </MultiParameter>
        </MultiParameter>
        <Coordinate x="380" y="720"/>
    </SimEntity>
    <SimEntity name="BasicTerrorist" type="diskit.BasicTerrorist">
        <MultiParameter type="diskit.Vec3d">
            <TerminalParameter type="double" value="-2500"/>
            <TerminalParameter type="double" value="-4300"/>
            <TerminalParameter type="double" value="0"/>
        </MultiParameter>
        <TerminalParameter type="double" value="30"/>
        <TerminalParameter type="int" value="600"/>
        <MultiParameter type="diskit.Vec3d[]">
            <MultiParameter type="diskit.Vec3d">
                <TerminalParameter type="double" value="-1556"/>
                <TerminalParameter type="double" value="-935"/>
                <TerminalParameter type="double" value="0"/>
            </MultiParameter>
            <MultiParameter type="diskit.Vec3d">
                <TerminalParameter type="double" value="-2043.989"/>
                <TerminalParameter type="double" value="-91.335"/>
                <TerminalParameter type="double" value="0"/>
            </MultiParameter>
        </MultiParameter>
        <TerminalParameter type="double" value="10"/>
        <Coordinate x="20" y="280"/>
    </SimEntity>
    <SimEntity name="OilTanker" type="diskit.HVU">
        <MultiParameter type="diskit.Vec3d">
            <TerminalParameter type="double" value="-2043.989"/>
            <TerminalParameter type="double" value="-91.335"/>
            <TerminalParameter type="double" value="0"/>
        </MultiParameter>
        <TerminalParameter type="double" value="0"/>
        <TerminalParameter type="int" value="300"/>
        <Coordinate x="60" y="410"/>
    </SimEntity>
    <SimEntity name="X3DCreateObstacles" type="diskit.util.X3DCreateObstacles">
        <TerminalParameter type="boolean" value="true"/>
        <TerminalParameter type="java.lang.String" value="../DISKIT/IITSEC2005/x3d/ABOT/"/>
        <Coordinate x="250" y="730"/>
    </SimEntity>
    <SimEventListenerConnection listener="ScenarioManager" source="RHIB1"/>
    <SimEventListenerConnection listener="ScenarioManager" source="DISPacketSender"/>
    <SimEventListenerConnection listener="RHIB1" source="SceneZoneCreator"/>
    <SimEventListenerConnection listener="ScenarioManager" source="SuperCobra"/>
    <SimEventListenerConnection listener="SuperCobra" source="SceneZoneCreator"/>
    <SimEventListenerConnection listener="DDG1" source="SceneZoneCreator"/>
    <SimEventListenerConnection listener="DDG2" source="SceneZoneCreator"/>
    <SimEventListenerConnection listener="RHIB2" source="SceneZoneCreator"/>
    <SimEventListenerConnection listener="ScenarioManager" source="RHIB2"/>
    <SimEventListenerConnection listener="CommerShip1" source="SceneZoneCreator"/>
    <SimEventListenerConnection listener="ScenarioManager" source="CommerShip1"/>
    <SimEventListenerConnection listener="CommerShip2" source="SceneZoneCreator"/>
    <SimEventListenerConnection listener="ScenarioManager" source="CommerShip2"/>
    <SimEventListenerConnection listener="ScenarioManager" source="DDG1"/>
    <SimEventListenerConnection listener="ScenarioManager" source="DDG2"/>
    <SimEventListenerConnection listener="Dhow1" source="DhowTraffic"/>
    <SimEventListenerConnection listener="Dhow2" source="DhowTraffic"/>
    <SimEventListenerConnection listener="Dhow3" source="DhowTraffic"/>
    <SimEventListenerConnection listener="Dhow4" source="DhowTraffic"/>
    <SimEventListenerConnection listener="Dhow5" source="DhowTraffic"/>
    <SimEventListenerConnection listener="Dhow6" source="DhowTraffic"/>
    <SimEventListenerConnection listener="ScenarioManager" source="Dhow1"/>
    <SimEventListenerConnection listener="ScenarioManager" source="Dhow2"/>
    <SimEventListenerConnection listener="ScenarioManager" source="Dhow3"/>
    <SimEventListenerConnection listener="ScenarioManager" source="Dhow4"/>
    <SimEventListenerConnection listener="ScenarioManager" source="Dhow5"/>
    <SimEventListenerConnection listener="ScenarioManager" source="Dhow6"/>
    <SimEventListenerConnection listener="BTB16" source="ABOTWest"/>
    <SimEventListenerConnection listener="BTB17" source="ABOTEast"/>
    <SimEventListenerConnection listener="RHIB2" source="BTB17"/>
    <SimEventListenerConnection listener="RHIB1" source="BTB16"/>
    <SimEventListenerConnection listener="ScenarioManager" source="ABOTObstacles"/>
    <SimEventListenerConnection listener="ScenarioManager" source="ABOTWest"/>
    <SimEventListenerConnection listener="ScenarioManager" source="ABOTEast"/>
    <SimEventListenerConnection listener="ScenarioManager" source="BasicTerrorist"/>
    <SimEventListenerConnection listener="ScenarioManager" source="OilTanker"/>
    <SimEventListenerConnection listener="X3DCreateObstacles" source="ABOTObstacles"/>
    <Schedule stopTime="10000" verbose="false"/>
    <Experiment runsPerDesignPoint="1" timeout="5000" totalSamples="1"/>
</SimkitAssembly>

