<?xml version="1.0" encoding="UTF-8" standalone="yes"?>
<SimkitAssembly package="examples.diskit" version="1.0" name="DISServer3DTestAssembly" xsi:noNamespaceSchemaLocation="http://diana.gl.nps.navy.mil/Simkit/assembly.xsd" xmlns:xsi="http://www.w3.org/2001/XMLSchema-instance">
    <SimEntity name="SimServer3DTest_0" type="examples.diskit.SimServer3DTest">
        <TerminalParameter type="java.lang.String" value="239.0.0.5"/>
        <TerminalParameter type="int" value="1500"/>
        <TerminalParameter type="double" value=".001"/>
        <Coordinate y="189" x="285"/>
    </SimEntity>
    <PropertyChangeListener name="SimplePropertyDumper_1" type="simkit.util.SimplePropertyDumper">
        <Coordinate y="300" x="100"/>
    </PropertyChangeListener>
    <PropertyChangeListenerConnection property="" listener="SimplePropertyDumper_1" source="SimServer3DTest_0"/>
    <Output entity="SimServer3DTest_0"/>
    <Schedule verbose="false" stopTime="100."/>
</SimkitAssembly>

